loadspinner/__init__.py
loadspinner/_spinners.py
loadspinner/tools/demo.py
loadspinner/tools/preview.py
loadspinner-0.6.dist-info/LICENSE
loadspinner-0.6.dist-info/METADATA
loadspinner-0.6.dist-info/WHEEL
loadspinner-0.6.dist-info/top_level.txt
loadspinner-0.6.dist-info/RECORD
