Metadata-Version: 2.1
Name: loadspinner
Version: 0.6
Summary: a CLI based loading spinner.
Home-page: https://github.com/xyzpw/loadspinner/
Author: xyzpw
Maintainer: xyzpw
License: MIT
Keywords: loading,loader,progress,throbber,spinner
Classifier: Programming Language :: Python :: 3
Classifier: Programming Language :: Python :: 3.8
Classifier: Programming Language :: Python :: 3.9
Classifier: Programming Language :: Python :: 3.10
Classifier: Programming Language :: Python :: 3.11
Classifier: Topic :: Utilities
Classifier: Topic :: Terminals
Classifier: Environment :: Console
Classifier: Environment :: Console :: Curses
Classifier: Intended Audience :: Developers
License-File: LICENSE
